.coveragerc
.pre-commit-config.yaml
.readthedocs.yml
.travis.yml
AUTHORS
CODE_OF_CONDUCT.md
CONTRIBUTING.md
ChangeLog
LICENSE
README.md
pyproject.toml
requirements-dev.txt
requirements.txt
setup.cfg
setup.py
docs/Makefile
docs/changelog.rst
docs/comparisons.md
docs/concepts.md
docs/conf.py
docs/contribute.rst
docs/features.md
docs/index.rst
docs/make.bat
docs/readme.rst
docs/requirements.txt
docs/usage.md
docs/_static/kirby-components.png
docs/_static/kirby-processes.png
dummies/dummy/setup.py
dummies/dummy/dummykirby/__init__.py
dummies/dummy/dummykirby/__main__.py
kirby/__init__.py
kirby/cli.py
kirby/demo.py
kirby/exc.py
kirby.egg-info/PKG-INFO
kirby.egg-info/SOURCES.txt
kirby.egg-info/dependency_links.txt
kirby.egg-info/entry_points.txt
kirby.egg-info/not-zip-safe
kirby.egg-info/pbr.json
kirby.egg-info/requires.txt
kirby.egg-info/top_level.txt
kirby/api/__init__.py
kirby/api/context.py
kirby/api/log.py
kirby/api/queue.py
kirby/api/testing.py
kirby/api/ext/__init__.py
kirby/api/ext/topic.py
kirby/api/ext/webclient.py
kirby/models/__init__.py
kirby/models/security.py
kirby/supervisor/__init__.py
kirby/supervisor/arbiter.py
kirby/supervisor/election.py
kirby/supervisor/executor.py
kirby/supervisor/scheduler.py
kirby/templates/kirby_master.html
kirby/templates/admin/index.html
kirby/templates/logs/index.html
kirby/templates/security/_macros.html
kirby/templates/security/_menu.html
kirby/templates/security/_messages.html
kirby/templates/security/change_password.html
kirby/templates/security/forgot_password.html
kirby/templates/security/login_user.html
kirby/templates/security/register_user.html
kirby/templates/security/reset_password.html
kirby/templates/security/send_confirmation.html
kirby/templates/security/send_login.html
kirby/templates/security/email/reset_instructions.html
kirby/web/__init__.py
kirby/web/admin.py
kirby/web/endpoints.py
kirby/web/forms.py
tests/conftest.py
tests/test_election.py
tests/test_endpoints.py
tests/test_executor.py
tests/test_models.py
tests/test_process_arbiter.py
tests/test_scheduler.py
tests/test_user.py
tests/data/sample_jobs_request.txt
tests/data/sample_single_job.txt
tests/tests_api/conftest.py
tests/tests_api/test_api.py
