Metadata-Version: 1.0
Name: kirby
Version: 0.0.1.dev190
Summary: Kafka-based Stream Processing Framework
Home-page: http://kirby.readthedocs.io
Author: Adimian
Author-email: contact@adimian.com
License: UNKNOWN
Platform: UNKNOWN
